{"id":211,"title_ru":"Французская Полинезия","title_en":"French Polynesia","cities":[{"id":4905213,"title_ru":"Afaahiti","title_en":"Afaahiti"},{"id":4905211,"title_ru":"Afareaitu","title_en":"Afareaitu"},{"id":4905209,"title_ru":"Afatauri","title_en":"Afatauri"},{"id":4905208,"title_ru":"Ahurei","title_en":"Ahurei"},{"id":4904790,"title_ru":"Akamaru","title_en":"Akamaru"},{"id":4904783,"title_ru":"Akaputu","title_en":"Akaputu"},{"id":4905207,"title_ru":"Amaru","title_en":"Amaru"},{"id":5421331,"title_ru":"Anaa","title_en":"Anaa"},{"id":4904815,"title_ru":"Anaho","title_en":"Anaho"},{"id":4897462,"title_ru":"Anapoo","title_en":"Anapoo"},{"id":4905206,"title_ru":"Anapoto","title_en":"Anapoto"},{"id":4905205,"title_ru":"Anatonu","title_en":"Anatonu"},{"id":4905203,"title_ru":"Anau","title_en":"Anau"},{"id":4904791,"title_ru":"Anganui","title_en":"Anganui"},{"id":4905201,"title_ru":"Anua","title_en":"Anua"},{"id":4905200,"title_ru":"Aoua","title_en":"Aoua"},{"id":4904782,"title_ru":"Apeakava","title_en":"Apeakava"},{"id":4905199,"title_ru":"Apihaa","title_en":"Apihaa"},{"id":4905198,"title_ru":"Apomaoro","title_en":"Apomaoro"},{"id":4905197,"title_ru":"Arahiri","title_en":"Arahiri"},{"id":4905196,"title_ru":"Araiteva","title_en":"Araiteva"},{"id":4905195,"title_ru":"Araito","title_en":"Araito"},{"id":4905194,"title_ru":"Area","title_en":"Area"},{"id":4905193,"title_ru":"Arue","title_en":"Arue"},{"id":4905191,"title_ru":"Ataiti","title_en":"Ataiti"},{"id":4904781,"title_ru":"Atiaoha","title_en":"Atiaoha"},{"id":4905190,"title_ru":"Atihiva","title_en":"Atihiva"},{"id":4904794,"title_ru":"Atihoi","title_en":"Atihoi"},{"id":4905189,"title_ru":"Atimaono","title_en":"Atimaono"},{"id":4905188,"title_ru":"Atipiti","title_en":"Atipiti"},{"id":4904780,"title_ru":"Atirikigaro","title_en":"Atirikigaro"},{"id":4904779,"title_ru":"Atituiti","title_en":"Atituiti"},{"id":4905186,"title_ru":"Atiue","title_en":"Atiue"},{"id":4897461,"title_ru":"Atuona","title_en":"Atuona"},{"id":4905185,"title_ru":"Auaue","title_en":"Auaue"},{"id":4904778,"title_ru":"Auorotini","title_en":"Auorotini"},{"id":4905184,"title_ru":"Auti","title_en":"Auti"},{"id":4905183,"title_ru":"Avae","title_en":"Avae"},{"id":4905182,"title_ru":"Avatoru","title_en":"Avatoru"},{"id":4905181,"title_ru":"Avera","title_en":"Avera"},{"id":4897460,"title_ru":"Clipperton Island","title_en":"Clipperton Island"},{"id":5308548,"title_ru":"Faa'a","title_en":"Faa'a"},{"id":4905180,"title_ru":"Faaa","title_en":"Faaa"},{"id":4905178,"title_ru":"Faanoa","title_en":"Faanoa"},{"id":4905177,"title_ru":"Faanui","title_en":"Faanui"},{"id":4905175,"title_ru":"Faaone","title_en":"Faaone"},{"id":4905173,"title_ru":"Faarumai","title_en":"Faarumai"},{"id":4905172,"title_ru":"Faatautia","title_en":"Faatautia"},{"id":4905171,"title_ru":"Faauanu","title_en":"Faauanu"},{"id":4904777,"title_ru":"Fakamaru","title_en":"Fakamaru"},{"id":4905170,"title_ru":"Fakatopatere","title_en":"Fakatopatere"},{"id":4905169,"title_ru":"Farauo","title_en":"Farauo"},{"id":4905168,"title_ru":"Fare","title_en":"Fare"},{"id":4905167,"title_ru":"Fareeru","title_en":"Fareeru"},{"id":4905166,"title_ru":"Farehau","title_en":"Farehau"},{"id":4905164,"title_ru":"Faremi","title_en":"Faremi"},{"id":4905163,"title_ru":"Fareorea","title_en":"Fareorea"},{"id":4905162,"title_ru":"Fariipiti","title_en":"Fariipiti"},{"id":4905161,"title_ru":"Fitii","title_en":"Fitii"},{"id":1703251,"title_ru":"Fort-de-France","title_en":"Fort-de-France"},{"id":4904775,"title_ru":"Gahutu","title_en":"Gahutu"},{"id":4904798,"title_ru":"Gahutu Tenohu","title_en":"Gahutu Tenohu"},{"id":4904793,"title_ru":"Ganoa","title_en":"Ganoa"},{"id":4905160,"title_ru":"Garumaoa","title_en":"Garumaoa"},{"id":4904796,"title_ru":"Gataha","title_en":"Gataha"},{"id":4904774,"title_ru":"Gatavaké","title_en":"Gatavaké"},{"id":4897459,"title_ru":"Haaoipu","title_en":"Haaoipu"},{"id":4905159,"title_ru":"Haapape","title_en":"Haapape"},{"id":4905158,"title_ru":"Haapiti","title_en":"Haapiti"},{"id":4905156,"title_ru":"Haapu","title_en":"Haapu"},{"id":4905155,"title_ru":"Haapupuni","title_en":"Haapupuni"},{"id":4904813,"title_ru":"Haka Puuae","title_en":"Haka Puuae"},{"id":4897458,"title_ru":"Hakamui","title_en":"Hakamui"},{"id":4904814,"title_ru":"Hakapehi","title_en":"Hakapehi"},{"id":4904812,"title_ru":"Hakaui","title_en":"Hakaui"},{"id":4905154,"title_ru":"Hamuta","title_en":"Hamuta"},{"id":4897455,"title_ru":"Hana te Fau","title_en":"Hana te Fau"},{"id":4897454,"title_ru":"Hana Teio","title_en":"Hana Teio"},{"id":4904773,"title_ru":"Hana Tuuna","title_en":"Hana Tuuna"},{"id":4897456,"title_ru":"Hana-moe-noa","title_en":"Hana-moe-noa"},{"id":4897457,"title_ru":"Hanamiai","title_en":"Hanamiai"},{"id":4897453,"title_ru":"Hanatetena","title_en":"Hanatetena"},{"id":4897452,"title_ru":"Hanaui","title_en":"Hanaui"},{"id":4904772,"title_ru":"Hanavave","title_en":"Hanavave"},{"id":4904811,"title_ru":"Hanga Haa","title_en":"Hanga Haa"},{"id":4897451,"title_ru":"Hapatoni","title_en":"Hapatoni"},{"id":4905153,"title_ru":"Hatinua","title_en":"Hatinua"},{"id":4905152,"title_ru":"Hauturua","title_en":"Hauturua"},{"id":4905148,"title_ru":"Hiti Mahaua","title_en":"Hiti Mahaua"},{"id":4905151,"title_ru":"Hitiaa","title_en":"Hitiaa"},{"id":4904810,"title_ru":"Hooumi","title_en":"Hooumi"},{"id":4905147,"title_ru":"Hotopuu","title_en":"Hotopuu"},{"id":4905146,"title_ru":"Houroumanou","title_en":"Houroumanou"},{"id":4905145,"title_ru":"Huahine","title_en":"Huahine"},{"id":4905144,"title_ru":"Huau","title_en":"Huau"},{"id":4905143,"title_ru":"Ikitake","title_en":"Ikitake"},{"id":4905139,"title_ru":"Iumaru","title_en":"Iumaru"},{"id":4897449,"title_ru":"Ivaiva Nui","title_en":"Ivaiva Nui"},{"id":4904795,"title_ru":"Kairori","title_en":"Kairori"},{"id":4905138,"title_ru":"Katiro","title_en":"Katiro"},{"id":4904770,"title_ru":"Kirimiro","title_en":"Kirimiro"},{"id":4904792,"title_ru":"Kokohue","title_en":"Kokohue"},{"id":4905137,"title_ru":"Lauiaru","title_en":"Lauiaru"},{"id":4905136,"title_ru":"Maaea","title_en":"Maaea"},{"id":4905135,"title_ru":"Maatea","title_en":"Maatea"},{"id":4905133,"title_ru":"Mahaena","title_en":"Mahaena"},{"id":4905131,"title_ru":"Mahaiutea","title_en":"Mahaiutea"},{"id":4905130,"title_ru":"Mahanatoa","title_en":"Mahanatoa"},{"id":5325840,"title_ru":"Maharepa","title_en":"Maharepa"},{"id":4905129,"title_ru":"Maheva","title_en":"Maheva"},{"id":4905128,"title_ru":"Mahina","title_en":"Mahina"},{"id":4905126,"title_ru":"Mahu","title_en":"Mahu"},{"id":4905125,"title_ru":"Maraa","title_en":"Maraa"},{"id":4905124,"title_ru":"Maraeapai","title_en":"Maraeapai"},{"id":4905123,"title_ru":"Marepa","title_en":"Marepa"},{"id":4905122,"title_ru":"Mariuti","title_en":"Mariuti"},{"id":4905121,"title_ru":"Maroe","title_en":"Maroe"},{"id":4905120,"title_ru":"Matahiva","title_en":"Matahiva"},{"id":4905118,"title_ru":"Mataiva","title_en":"Mataiva"},{"id":4905116,"title_ru":"Mataorio","title_en":"Mataorio"},{"id":4905114,"title_ru":"Mataura","title_en":"Mataura"},{"id":4905113,"title_ru":"Matiti","title_en":"Matiti"},{"id":4905112,"title_ru":"Matotea","title_en":"Matotea"},{"id":4905111,"title_ru":"Matura","title_en":"Matura"},{"id":4905110,"title_ru":"Mitirapa","title_en":"Mitirapa"},{"id":4905109,"title_ru":"Moerai","title_en":"Moerai"},{"id":4897448,"title_ru":"Motopu","title_en":"Motopu"},{"id":4905021,"title_ru":"Motu Taiahu","title_en":"Motu Taiahu"},{"id":4905108,"title_ru":"Motu Ura","title_en":"Motu Ura"},{"id":4897447,"title_ru":"Nahoe","title_en":"Nahoe"},{"id":4905107,"title_ru":"Nairiri","title_en":"Nairiri"},{"id":4905106,"title_ru":"Niumaa","title_en":"Niumaa"},{"id":4905105,"title_ru":"Niuporiri","title_en":"Niuporiri"},{"id":4905104,"title_ru":"Niutahi","title_en":"Niutahi"},{"id":4905103,"title_ru":"Nivee","title_en":"Nivee"},{"id":4905101,"title_ru":"Nurehia","title_en":"Nurehia"},{"id":4905100,"title_ru":"Nutae","title_en":"Nutae"},{"id":4905099,"title_ru":"Oae","title_en":"Oae"},{"id":4897446,"title_ru":"Oehau","title_en":"Oehau"},{"id":4905098,"title_ru":"Ofaiharata","title_en":"Ofaiharata"},{"id":4905097,"title_ru":"Ohava","title_en":"Ohava"},{"id":4905096,"title_ru":"Ohomo","title_en":"Ohomo"},{"id":4904769,"title_ru":"Omoa","title_en":"Omoa"},{"id":4905095,"title_ru":"Omuara","title_en":"Omuara"},{"id":4905094,"title_ru":"Onoheha","title_en":"Onoheha"},{"id":4905093,"title_ru":"Opaura","title_en":"Opaura"},{"id":4905092,"title_ru":"Oponu","title_en":"Oponu"},{"id":4905091,"title_ru":"Orofara","title_en":"Orofara"},{"id":4905090,"title_ru":"Oroiri","title_en":"Oroiri"},{"id":4905089,"title_ru":"Orouau","title_en":"Orouau"},{"id":4905088,"title_ru":"Orufara","title_en":"Orufara"},{"id":4905087,"title_ru":"Otepa","title_en":"Otepa"},{"id":4905086,"title_ru":"Otiaroa","title_en":"Otiaroa"},{"id":4905085,"title_ru":"Otumai","title_en":"Otumai"},{"id":4905084,"title_ru":"Otuofai","title_en":"Otuofai"},{"id":4905083,"title_ru":"Otutara","title_en":"Otutara"},{"id":4904768,"title_ru":"Ouia","title_en":"Ouia"},{"id":4905082,"title_ru":"Outu Maoro","title_en":"Outu Maoro"},{"id":4905081,"title_ru":"Paea","title_en":"Paea"},{"id":4905079,"title_ru":"Paeau","title_en":"Paeau"},{"id":5165673,"title_ru":"Paeua","title_en":"Paeua"},{"id":4905078,"title_ru":"Pahiti","title_en":"Pahiti"},{"id":4905077,"title_ru":"Pahonu","title_en":"Pahonu"},{"id":4905076,"title_ru":"Pahua","title_en":"Pahua"},{"id":4905075,"title_ru":"Paiouma","title_en":"Paiouma"},{"id":4905074,"title_ru":"Paofai","title_en":"Paofai"},{"id":4905073,"title_ru":"Paopao","title_en":"Paopao"},{"id":4905072,"title_ru":"Papao","title_en":"Papao"},{"id":4905070,"title_ru":"Paparevo","title_en":"Paparevo"},{"id":4905069,"title_ru":"Papawa","title_en":"Papawa"},{"id":4905067,"title_ru":"Papeete","title_en":"Papeete"},{"id":4905066,"title_ru":"Papehee","title_en":"Papehee"},{"id":4905064,"title_ru":"Papetoai","title_en":"Papetoai"},{"id":4905062,"title_ru":"Paraeo","title_en":"Paraeo"},{"id":4905061,"title_ru":"Paraiore","title_en":"Paraiore"},{"id":4905060,"title_ru":"Paraohumu","title_en":"Paraohumu"},{"id":4905059,"title_ru":"Paraoro","title_en":"Paraoro"},{"id":4905058,"title_ru":"Parari","title_en":"Parari"},{"id":4905057,"title_ru":"Patere","title_en":"Patere"},{"id":4905056,"title_ru":"Patio","title_en":"Patio"},{"id":4905054,"title_ru":"Patu Patu","title_en":"Patu Patu"},{"id":4905055,"title_ru":"Patuarepa","title_en":"Patuarepa"},{"id":4905053,"title_ru":"Paturoa","title_en":"Paturoa"},{"id":4905052,"title_ru":"Patutoa","title_en":"Patutoa"},{"id":4905051,"title_ru":"Paui","title_en":"Paui"},{"id":4905050,"title_ru":"Pehoa","title_en":"Pehoa"},{"id":4905049,"title_ru":"Petou","title_en":"Petou"},{"id":4905048,"title_ru":"Pierre","title_en":"Pierre"},{"id":4905047,"title_ru":"Pihaa","title_en":"Pihaa"},{"id":4905046,"title_ru":"Pihaena","title_en":"Pihaena"},{"id":4905045,"title_ru":"Pipine","title_en":"Pipine"},{"id":4905044,"title_ru":"Pirae","title_en":"Pirae"},{"id":4905042,"title_ru":"Pouheva","title_en":"Pouheva"},{"id":4905041,"title_ru":"Poutei","title_en":"Poutei"},{"id":4905040,"title_ru":"Povai","title_en":"Povai"},{"id":4905039,"title_ru":"Puahua","title_en":"Puahua"},{"id":4905038,"title_ru":"Puaiti","title_en":"Puaiti"},{"id":4905037,"title_ru":"Pueu","title_en":"Pueu"},{"id":4905035,"title_ru":"Punaauia","title_en":"Punaauia"},{"id":4905033,"title_ru":"Putiara","title_en":"Putiara"},{"id":4905032,"title_ru":"Rairai","title_en":"Rairai"},{"id":4905031,"title_ru":"Rairua","title_en":"Rairua"},{"id":4905029,"title_ru":"Raitahiti","title_en":"Raitahiti"},{"id":4905028,"title_ru":"Rautini","title_en":"Rautini"},{"id":4904767,"title_ru":"Rikitea","title_en":"Rikitea"},{"id":4905027,"title_ru":"Rotoava","title_en":"Rotoava"},{"id":4904766,"title_ru":"Rouru","title_en":"Rouru"},{"id":4905026,"title_ru":"Sainte Amélie","title_en":"Sainte Amélie"},{"id":4905025,"title_ru":"Taapuna","title_en":"Taapuna"},{"id":5421332,"title_ru":"Tahaa","title_en":"Tahaa"},{"id":4905024,"title_ru":"Taharoa","title_en":"Taharoa"},{"id":4905023,"title_ru":"Tahateao","title_en":"Tahateao"},{"id":5421330,"title_ru":"Tahiti","title_en":"Tahiti"},{"id":4905022,"title_ru":"Tahueia","title_en":"Tahueia"},{"id":4904765,"title_ru":"Taiokai","title_en":"Taiokai"},{"id":4904764,"title_ru":"Taku","title_en":"Taku"},{"id":4905020,"title_ru":"Tamatoa","title_en":"Tamatoa"},{"id":4904789,"title_ru":"Taravao","title_en":"Taravao"},{"id":4905018,"title_ru":"Tarione","title_en":"Tarione"},{"id":4905017,"title_ru":"Tatoi","title_en":"Tatoi"},{"id":4897445,"title_ru":"Taua","title_en":"Taua"},{"id":4905016,"title_ru":"Taunoa","title_en":"Taunoa"},{"id":4905014,"title_ru":"Tautira","title_en":"Tautira"},{"id":4905012,"title_ru":"Taverea","title_en":"Taverea"},{"id":4905005,"title_ru":"Te Auae","title_en":"Te Auae"},{"id":4904988,"title_ru":"Te Rua Pua","title_en":"Te Rua Pua"},{"id":4905002,"title_ru":"Te-Fare-Arii","title_en":"Te-Fare-Arii"},{"id":4905011,"title_ru":"Teaharoa","title_en":"Teaharoa"},{"id":4905009,"title_ru":"Teahupoo","title_en":"Teahupoo"},{"id":4905008,"title_ru":"Teana","title_en":"Teana"},{"id":4905007,"title_ru":"Teapaa","title_en":"Teapaa"},{"id":4905004,"title_ru":"Teavaro","title_en":"Teavaro"},{"id":4905001,"title_ru":"Tefau","title_en":"Tefau"},{"id":4905000,"title_ru":"Tehekega","title_en":"Tehekega"},{"id":4904999,"title_ru":"Tehuarupe","title_en":"Tehuarupe"},{"id":4904998,"title_ru":"Temae","title_en":"Temae"},{"id":4904997,"title_ru":"Temao","title_en":"Temao"},{"id":4904996,"title_ru":"Teniuohiri","title_en":"Teniuohiri"},{"id":4904995,"title_ru":"Tenukupara","title_en":"Tenukupara"},{"id":4904763,"title_ru":"Teonemahina","title_en":"Teonemahina"},{"id":4904994,"title_ru":"Tepu","title_en":"Tepu"},{"id":4904993,"title_ru":"Tepukamaruia","title_en":"Tepukamaruia"},{"id":4904992,"title_ru":"Terehe","title_en":"Terehe"},{"id":4904991,"title_ru":"Tereporepo","title_en":"Tereporepo"},{"id":4904990,"title_ru":"Teruafaroa","title_en":"Teruafaroa"},{"id":4904989,"title_ru":"Teruamao","title_en":"Teruamao"},{"id":4904987,"title_ru":"Tetamanu","title_en":"Tetamanu"},{"id":4904986,"title_ru":"Tetira","title_en":"Tetira"},{"id":4904985,"title_ru":"Teuo","title_en":"Teuo"},{"id":4904984,"title_ru":"Tevaitoa","title_en":"Tevaitoa"},{"id":4904983,"title_ru":"Tiaraha","title_en":"Tiaraha"},{"id":4904982,"title_ru":"Tiarei","title_en":"Tiarei"},{"id":4904980,"title_ru":"Tiitau","title_en":"Tiitau"},{"id":4904979,"title_ru":"Tiomati","title_en":"Tiomati"},{"id":4904978,"title_ru":"Tipaerui","title_en":"Tipaerui"},{"id":4904977,"title_ru":"Tiputa","title_en":"Tiputa"},{"id":4904976,"title_ru":"Tiripoa","title_en":"Tiripoa"},{"id":4904975,"title_ru":"Toamara","title_en":"Toamara"},{"id":4904974,"title_ru":"Toanoano","title_en":"Toanoano"},{"id":4904973,"title_ru":"Toetoe","title_en":"Toetoe"},{"id":4904972,"title_ru":"Tohautu","title_en":"Tohautu"},{"id":4904971,"title_ru":"Toini","title_en":"Toini"},{"id":4904970,"title_ru":"Topitike","title_en":"Topitike"},{"id":4904969,"title_ru":"Tuara","title_en":"Tuara"},{"id":4904968,"title_ru":"Tuarea","title_en":"Tuarea"},{"id":4904967,"title_ru":"Tuete","title_en":"Tuete"},{"id":4904966,"title_ru":"Tuherahera","title_en":"Tuherahera"},{"id":4904965,"title_ru":"Tukuhora","title_en":"Tukuhora"},{"id":4904964,"title_ru":"Tupana","title_en":"Tupana"},{"id":4904963,"title_ru":"Tupapati","title_en":"Tupapati"},{"id":4904962,"title_ru":"Urihore","title_en":"Urihore"},{"id":4904961,"title_ru":"Uritutua","title_en":"Uritutua"},{"id":4904960,"title_ru":"Uturoa","title_en":"Uturoa"},{"id":4905711,"title_ru":"Vaïare","title_en":"Vaïare"},{"id":4904959,"title_ru":"Vaihi","title_en":"Vaihi"},{"id":4904958,"title_ru":"Vaionifa","title_en":"Vaionifa"},{"id":4904957,"title_ru":"Vaioperu","title_en":"Vaioperu"},{"id":4904956,"title_ru":"Vaiori","title_en":"Vaiori"},{"id":4904955,"title_ru":"Vaipeu","title_en":"Vaipeu"},{"id":4904954,"title_ru":"Vaipohe","title_en":"Vaipohe"},{"id":4904953,"title_ru":"Vairao","title_en":"Vairao"},{"id":4904951,"title_ru":"Vairo","title_en":"Vairo"},{"id":4904950,"title_ru":"Vairoa","title_en":"Vairoa"},{"id":4897444,"title_ru":"Vaitahu","title_en":"Vaitahu"},{"id":4904949,"title_ru":"Vaitape","title_en":"Vaitape"},{"id":4904948,"title_ru":"Vaitia","title_en":"Vaitia"},{"id":4904797,"title_ru":"Vaitinoua","title_en":"Vaitinoua"},{"id":4904947,"title_ru":"Vaitoare","title_en":"Vaitoare"},{"id":4904945,"title_ru":"Vaitona","title_en":"Vaitona"},{"id":4904944,"title_ru":"Vaitoto","title_en":"Vaitoto"},{"id":4904809,"title_ru":"Vaitu","title_en":"Vaitu"},{"id":4904943,"title_ru":"Vaitunanaa","title_en":"Vaitunanaa"},{"id":4904942,"title_ru":"Vaiuru","title_en":"Vaiuru"}]}