{"id":7,"title_ru":"Грузия","title_en":"Georgia","cities":[{"id":2400682,"title_ru":"Абано","title_en":"Abano"},{"id":1903032,"title_ru":"Абастумани","title_en":"Abastumani"},{"id":1707598,"title_ru":"Абаша","title_en":"Abasha"},{"id":1911280,"title_ru":"Абелиани","title_en":"Abeliani"},{"id":2400038,"title_ru":"Абукети","title_en":"Abuketi"},{"id":1929986,"title_ru":"Абул","title_en":"Abul"},{"id":2400001,"title_ru":"Абхазия","title_en":"Abkhazia"},{"id":21943,"title_ru":"Авранло","title_en":"Avranlo"},{"id":2400408,"title_ru":"Авчала","title_en":"Avchala"},{"id":1943890,"title_ru":"Агана","title_en":"Agana"},{"id":1903049,"title_ru":"Агара","title_en":"Agara"},{"id":2400683,"title_ru":"Агара","title_en":"Agara"},{"id":2400075,"title_ru":"Агараки","title_en":"Agaraki"},{"id":1913598,"title_ru":"Агтакля","title_en":"Agtaklya"},{"id":1951183,"title_ru":"Агудзера","title_en":"Agudzera"},{"id":2400037,"title_ru":"Аджария","title_en":"Adzharia"},{"id":2400002,"title_ru":"Адзюбжа","title_en":"Adzyubzha"},{"id":5470342,"title_ru":"Адлиа","title_en":"Adlia"},{"id":2400624,"title_ru":"Адыгены","title_en":"Adygeny"},{"id":5479517,"title_ru":"Ажара","title_en":"Azhara"},{"id":5470295,"title_ru":"Азаврети","title_en":"Azavreti"},{"id":2400625,"title_ru":"Азмана","title_en":"Azmana"},{"id":2400076,"title_ru":"Акти","title_en":"Akti"},{"id":2400003,"title_ru":"Акуаскя","title_en":"Akuaskya"},{"id":1705599,"title_ru":"Аластани","title_en":"Alastani"},{"id":1709659,"title_ru":"Алахадзы","title_en":"Alakhadzy"},{"id":5472524,"title_ru":"Алгети","title_en":"Algeti"},{"id":2400339,"title_ru":"Алексеевка","title_en":"Alexeevka"},{"id":2400484,"title_ru":"Алпана","title_en":"Alpana"},{"id":1935483,"title_ru":"Амбролаури","title_en":"Ambrolauri"},{"id":2400409,"title_ru":"Амга","title_en":"Amga"},{"id":2400340,"title_ru":"Амлеви","title_en":"Amlevi"},{"id":1708608,"title_ru":"Анага","title_en":"Anaga"},{"id":1955556,"title_ru":"Анаклия","title_en":"Anaklia"},{"id":1924931,"title_ru":"Анасеули","title_en":"Anaseuli"},{"id":2400627,"title_ru":"Анда","title_en":"Anda"},{"id":1949541,"title_ru":"Арагва","title_en":"Aragva"},{"id":5470359,"title_ru":"Араду","title_en":"Aradu"},{"id":1943406,"title_ru":"Аракич","title_en":"Arakich"},{"id":2400341,"title_ru":"Арджеван-Сарвани","title_en":"Ardzhevan-Sarvani"},{"id":5470352,"title_ru":"Арешперани","title_en":"Areshperani"},{"id":1918633,"title_ru":"Арцеви","title_en":"Artsevi"},{"id":2400410,"title_ru":"Арчило","title_en":"Archilo"},{"id":2400077,"title_ru":"Аскана","title_en":"Askana"},{"id":1917933,"title_ru":"Аспиндза","title_en":"Aspindza"},{"id":2400411,"title_ru":"Атнохи","title_en":"Atnokhi"},{"id":2400684,"title_ru":"Атоци","title_en":"Atotsi"},{"id":2400412,"title_ru":"Ахалгори","title_en":"Akhalgori"},{"id":1943743,"title_ru":"Ахалдаба","title_en":"Akhaldaba"},{"id":2400342,"title_ru":"Ахали-Зирбити","title_en":"Akhali-Zirbiti"},{"id":2400155,"title_ru":"Ахали-Тержола","title_en":"Akhali-Terzhola"},{"id":1933707,"title_ru":"Ахалкалаки","title_en":"Akhalkalaki"},{"id":5470320,"title_ru":"Ахалкахати","title_en":"Akhalkakhati"},{"id":1952087,"title_ru":"Ахалсопели","title_en":"Akhalsopeli"},{"id":2400685,"title_ru":"Ахалсопели","title_en":"Akhalsopeli"},{"id":2400413,"title_ru":"Ахалубани","title_en":"Akhalubani"},{"id":1958478,"title_ru":"Ахалцихе","title_en":"Akhaltsikhe"},{"id":10271,"title_ru":"Ахалшени","title_en":"Akhalsheni"},{"id":1704057,"title_ru":"Ахмета","title_en":"Akhmeta"},{"id":2400544,"title_ru":"Ахути","title_en":"Akhuti"},{"id":2400079,"title_ru":"Ацана","title_en":"Atsana"},{"id":5470331,"title_ru":"Ацкури","title_en":"Atskuri"},{"id":5470314,"title_ru":"Ачандара","title_en":"Achandara"},{"id":2400041,"title_ru":"Ачква","title_en":"Achkva"},{"id":5470361,"title_ru":"Ашкала","title_en":"Ashkala"},{"id":21486,"title_ru":"Бабанеури","title_en":"Babaneuri"},{"id":2400156,"title_ru":"Баби","title_en":"Babi"},{"id":5470315,"title_ru":"Бабушара","title_en":"Babushara"},{"id":5470296,"title_ru":"Бавра","title_en":"Bavra"},{"id":20229,"title_ru":"Багдати","title_en":"Bagdati"},{"id":1920772,"title_ru":"Базалети","title_en":"Bazaleti"},{"id":2400414,"title_ru":"Базуани","title_en":"Bazuani"},{"id":2400080,"title_ru":"Баилет","title_en":"Bailet"},{"id":1709605,"title_ru":"Бакуриани","title_en":"Bakuriani"},{"id":2400042,"title_ru":"Баладзейеби","title_en":"Baladzeyebi"},{"id":2400634,"title_ru":"Баланта","title_en":"Balanta"},{"id":2400005,"title_ru":"Бамбора","title_en":"Bambora"},{"id":5470297,"title_ru":"Баралети","title_en":"Baraleti"},{"id":2400159,"title_ru":"Барити","title_en":"Bariti"},{"id":2400081,"title_ru":"Басилети","title_en":"Basileti"},{"id":5470316,"title_ru":"Баслата","title_en":"Baslata"},{"id":1951095,"title_ru":"Баслаху","title_en":"Baslakhu"},{"id":21032,"title_ru":"Батуми","title_en":"Batumi"},{"id":2400082,"title_ru":"Бахви","title_en":"Bakhvi"},{"id":2400343,"title_ru":"Бахчалари","title_en":"Bakhchalari"},{"id":2400344,"title_ru":"Беврети","title_en":"Bevreti"},{"id":1519041,"title_ru":"Бедиани","title_en":"Bediani"},{"id":2400160,"title_ru":"Бежатубани","title_en":"Bezhatubani"},{"id":2400345,"title_ru":"Безакло","title_en":"Bezaklo"},{"id":2400686,"title_ru":"Бериджвари","title_en":"Beridzhvari"},{"id":2400687,"title_ru":"Бершуйети","title_en":"Bershuyeti"},{"id":1708102,"title_ru":"Бешташени","title_en":"Beshtasheni"},{"id":1966921,"title_ru":"Бзыпта","title_en":"Bzypta"},{"id":2400415,"title_ru":"Библиани","title_en":"Bibliani"},{"id":2400161,"title_ru":"Бига","title_en":"Biga"},{"id":2400008,"title_ru":"Блабырхуа","title_en":"Blabyrkhua"},{"id":5470351,"title_ru":"Бобоквати","title_en":"Bobokvati"},{"id":2400545,"title_ru":"Боботи","title_en":"Boboti"},{"id":2400416,"title_ru":"Богчвило","title_en":"Bogchvilo"},{"id":2400044,"title_ru":"Бодзаури","title_en":"Bodzauri"},{"id":22325,"title_ru":"Болниси","title_en":"Bolnisi"},{"id":6051,"title_ru":"Боржоми","title_en":"Borzhomi"},{"id":2400083,"title_ru":"Бохваури","title_en":"Bokhvauri"},{"id":2400486,"title_ru":"Бугеули","title_en":"Bugeuli"},{"id":2400084,"title_ru":"Букисцихе","title_en":"Bukistsikhe"},{"id":2400085,"title_ru":"Букнари","title_en":"Buknari"},{"id":2400417,"title_ru":"Булачаури","title_en":"Bulachauri"},{"id":2400348,"title_ru":"Бурдадзори","title_en":"Burdadzori"},{"id":2400086,"title_ru":"Бурнати","title_en":"Burnati"},{"id":2400418,"title_ru":"Бучукурта","title_en":"Buchukurta"},{"id":8439,"title_ru":"Вазиани","title_en":"Vaziani"},{"id":2400087,"title_ru":"Вакиджвари","title_en":"Vakidzhvari"},{"id":2400162,"title_ru":"Вакиса","title_en":"Vakisa"},{"id":20978,"title_ru":"Вале","title_en":"Vale"},{"id":2400088,"title_ru":"Ван-Зомлети","title_en":"Van-Zomleti"},{"id":2400688,"title_ru":"Ванати","title_en":"Vanati"},{"id":13123,"title_ru":"Вани","title_en":"Vani"},{"id":2400637,"title_ru":"Вани","title_en":"Vani"},{"id":2400638,"title_ru":"Вардевани","title_en":"Vardevani"},{"id":5479306,"title_ru":"Вардисубани","title_en":"Vardisubani"},{"id":2400639,"title_ru":"Варевани","title_en":"Varevani"},{"id":2400419,"title_ru":"Варцла","title_en":"Vartsla"},{"id":1708605,"title_ru":"Варче","title_en":"Varche"},{"id":2400546,"title_ru":"Ваха","title_en":"Vakha"},{"id":1947612,"title_ru":"Вачиани","title_en":"Vachiani"},{"id":2400487,"title_ru":"Велеви","title_en":"Velevi"},{"id":5470317,"title_ru":"Верхняя Эшера","title_en":"Verkhnyaya Eshera"},{"id":1934041,"title_ru":"Владимировка","title_en":"Vladimirovka"},{"id":2400689,"title_ru":"Вуаллаг-Бакарта","title_en":"Vuallag-Bakarta"},{"id":2400547,"title_ru":"Гагма-Кариата","title_en":"Gagma-Kariata"},{"id":1961775,"title_ru":"Гагра","title_en":"Gagra"},{"id":2400488,"title_ru":"Гадамши","title_en":"Gadamshi"},{"id":2400489,"title_ru":"Гадиши","title_en":"Gadishi"},{"id":2400640,"title_ru":"Гадо","title_en":"Gado"},{"id":1963665,"title_ru":"Гал","title_en":"Gal"},{"id":2400421,"title_ru":"Галавани","title_en":"Galavani"},{"id":5470360,"title_ru":"Гамогма-Пирвели-Хорга","title_en":"Gamogma-Pirveli-Khorga"},{"id":5470194,"title_ru":"Ганарджиис-Мухури","title_en":"Ganardzhiis-Mukhuri"},{"id":1708548,"title_ru":"Ганахлеба","title_en":"Ganakhleba"},{"id":1707513,"title_ru":"Гандза","title_en":"Gandza"},{"id":2400641,"title_ru":"Гандзани","title_en":"Gandzani"},{"id":2400420,"title_ru":"Ганиси","title_en":"Ganisi"},{"id":2400691,"title_ru":"Гаргали","title_en":"Gargali"},{"id":20758,"title_ru":"Гардабани","title_en":"Gardabani"},{"id":2400692,"title_ru":"Гаристави","title_en":"Garistavi"},{"id":2400164,"title_ru":"Гвазаури","title_en":"Gvazauri"},{"id":2400045,"title_ru":"Гвара","title_en":"Gvara"},{"id":2400422,"title_ru":"Гвелети","title_en":"Gveleti"},{"id":2400490,"title_ru":"Гвесо","title_en":"Gveso"},{"id":2400089,"title_ru":"Гвимбалаури","title_en":"Gvimbalauri"},{"id":2400491,"title_ru":"Гвириши","title_en":"Gvirishi"},{"id":2400492,"title_ru":"Геби","title_en":"Gebi"},{"id":2400350,"title_ru":"Гедагдаги","title_en":"Gedagdagi"},{"id":2400548,"title_ru":"Гешдери","title_en":"Geshderi"},{"id":2400642,"title_ru":"Гиоргицминда","title_en":"Giorgitsminda"},{"id":2400693,"title_ru":"Гнасури","title_en":"Gnasuri"},{"id":5473136,"title_ru":"Гогинаури","title_en":"Goginauri"},{"id":2400165,"title_ru":"Гогни","title_en":"Gogni"},{"id":1922105,"title_ru":"Годолар","title_en":"Godolar"},{"id":2400643,"title_ru":"Гокио","title_en":"Gokio"},{"id":2400166,"title_ru":"Голатубани","title_en":"Golatubani"},{"id":1705705,"title_ru":"Гомбори","title_en":"Gombori"},{"id":2400493,"title_ru":"Гоми","title_en":"Gomi"},{"id":2400644,"title_ru":"Гомна","title_en":"Gomna"},{"id":2400167,"title_ru":"Гона","title_en":"Gona"},{"id":1928630,"title_ru":"Гонио","title_en":"Gonio"},{"id":2400090,"title_ru":"Горабережоули","title_en":"Goraberezhouli"},{"id":2400423,"title_ru":"Горга","title_en":"Gorga"},{"id":2400645,"title_ru":"Горгули","title_en":"Gorguli"},{"id":1933284,"title_ru":"Гореловка","title_en":"Gorelovka"},{"id":1968340,"title_ru":"Гори","title_en":"Gori"},{"id":5422759,"title_ru":"Горисубани","title_en":"Gorisubani"},{"id":2400647,"title_ru":"Гортубани","title_en":"Gortubani"},{"id":2400091,"title_ru":"Грамагеле","title_en":"Gramagele"},{"id":2400092,"title_ru":"Григолети","title_en":"Grigoleti"},{"id":2400093,"title_ru":"Грмагеле","title_en":"Grmagele"},{"id":2400351,"title_ru":"Гударехи","title_en":"Gudarekhi"},{"id":1904269,"title_ru":"Гудаури","title_en":"Gudauri"},{"id":1971110,"title_ru":"Гудаута","title_en":"Gudauta"},{"id":2400690,"title_ru":"Гудиси","title_en":"Gudisi"},{"id":2400424,"title_ru":"Гулелеби","title_en":"Gulelebi"},{"id":2400425,"title_ru":"Гули","title_en":"Guli"},{"id":2400648,"title_ru":"Гуликами","title_en":"Gulikami"},{"id":1714532,"title_ru":"Гульрипш","title_en":"Gulripsh"},{"id":2400352,"title_ru":"Гумбати","title_en":"Gumbati"},{"id":5470293,"title_ru":"Гумбурдо","title_en":"Gumburdo"},{"id":5470313,"title_ru":"Гумиста","title_en":"Gumista"},{"id":1904506,"title_ru":"Гуниа-Кала","title_en":"Gunia-Kala"},{"id":12006,"title_ru":"Гурджаани","title_en":"Gurdzhaani"},{"id":2400047,"title_ru":"Гурдзаули","title_en":"Gurdzauli"},{"id":2400094,"title_ru":"Гурианта","title_en":"Gurianta"},{"id":2400074,"title_ru":"Гурийский","title_en":"Guriysky"},{"id":2400426,"title_ru":"Гуро","title_en":"Guro"},{"id":2400095,"title_ru":"Гутури","title_en":"Guturi"},{"id":1713433,"title_ru":"Гячрыпш","title_en":"Gyachrypsh"},{"id":2400096,"title_ru":"Даблацихе","title_en":"Dablatsikhe"},{"id":5470346,"title_ru":"Давитиани","title_en":"Davitiani"},{"id":2400427,"title_ru":"Давитурни","title_en":"Daviturni"},{"id":2400354,"title_ru":"Дагет-Хачини","title_en":"Daget-Khachini"},{"id":1941006,"title_ru":"Дадеш","title_en":"Dadesh"},{"id":1901963,"title_ru":"Дамала","title_en":"Damala"},{"id":2400355,"title_ru":"Дамиа-Гиаурархи","title_en":"Damia-Giaurarkhi"},{"id":5468416,"title_ru":"Дарбази","title_en":"Darbazi"},{"id":2400097,"title_ru":"Двабзу","title_en":"Dvabzu"},{"id":2400695,"title_ru":"Двани","title_en":"Dvani"},{"id":2400549,"title_ru":"Девра","title_en":"Devra"},{"id":1967502,"title_ru":"Дедоплисцкаро","title_en":"Dedoplistskaro"},{"id":2400168,"title_ru":"Дерчи","title_en":"Derchi"},{"id":1925329,"title_ru":"Джава","title_en":"Dzhava"},{"id":2400356,"title_ru":"Джавахи","title_en":"Dzhavakhi"},{"id":2400494,"title_ru":"Джахундери","title_en":"Dzhakhunderi"},{"id":2400170,"title_ru":"Джвариса","title_en":"Dzhvarisa"},{"id":1703497,"title_ru":"Джиграшени","title_en":"Dzhigrasheni"},{"id":2400550,"title_ru":"Джихашкари","title_en":"Dzhikhashkari"},{"id":2400098,"title_ru":"Джумати","title_en":"Dzhumati"},{"id":2400551,"title_ru":"Джумити","title_en":"Dzhumiti"},{"id":2400697,"title_ru":"Дзалиси","title_en":"Dzalisi"},{"id":2400698,"title_ru":"Дзарцеми","title_en":"Dzartsemi"},{"id":2400699,"title_ru":"Дзвели-Канда","title_en":"Dzveli-Kanda"},{"id":2400700,"title_ru":"Дзевера","title_en":"Dzevera"},{"id":2400099,"title_ru":"Дзимити","title_en":"Dzimiti"},{"id":2400100,"title_ru":"Дзириджумати","title_en":"Dziridzhumati"},{"id":2400171,"title_ru":"Дзулухи","title_en":"Dzulukhi"},{"id":2400172,"title_ru":"Дидвела","title_en":"Didvela"},{"id":2400428,"title_ru":"Дидгори","title_en":"Didgori"},{"id":2400429,"title_ru":"Дидебаани","title_en":"Didebaani"},{"id":2400650,"title_ru":"Диди Памаджи","title_en":"Didi Pamadzhi"},{"id":2400651,"title_ru":"Диди-Агара","title_en":"Didi-Agara"},{"id":2400358,"title_ru":"Диди-Беглари","title_en":"Didi-Beglari"},{"id":5471713,"title_ru":"Диди-Дманиси","title_en":"Didi-Dmanisi"},{"id":2400701,"title_ru":"Диди-Келети","title_en":"Didi-Keleti"},{"id":2400359,"title_ru":"Диди-Клдеиси","title_en":"Didi-Kldeisi"},{"id":2400652,"title_ru":"Диди-Митарби","title_en":"Didi-Mitarbi"},{"id":5471631,"title_ru":"Диди-Муганло","title_en":"Didi-Muganlo"},{"id":5470294,"title_ru":"Диди-Самсари (Большой Самсар)","title_en":"Didi-Samsari (bolshoy Samsar)"},{"id":5476621,"title_ru":"Диди-Ханчали","title_en":"Didi-Khanchali"},{"id":5470356,"title_ru":"Диди-Чкони","title_en":"Didi-Chkoni"},{"id":1924628,"title_ru":"Диди-Шираки","title_en":"Didi-Shiraki"},{"id":2400552,"title_ru":"Дизи","title_en":"Dizi"},{"id":5470292,"title_ru":"Дилиска","title_en":"Diliska"},{"id":2400653,"title_ru":"Дилити","title_en":"Diliti"},{"id":1935070,"title_ru":"Дими","title_en":"Dimi"},{"id":2400702,"title_ru":"Дирби","title_en":"Dirbi"},{"id":1902557,"title_ru":"Дманиси","title_en":"Dmanisi"},{"id":2400703,"title_ru":"Доглаури","title_en":"Doglauri"},{"id":2400048,"title_ru":"Дологани","title_en":"Dologani"},{"id":1935775,"title_ru":"Дранда","title_en":"Dranda"},{"id":2400361,"title_ru":"Дре","title_en":"Dre"},{"id":2400014,"title_ru":"Дурипш","title_en":"Duripsh"},{"id":1918116,"title_ru":"Душети","title_en":"Dusheti"},{"id":2400654,"title_ru":"Ефремовка","title_en":"Efremovka"},{"id":2400431,"title_ru":"Жебота","title_en":"Zhebota"},{"id":1935857,"title_ru":"Жинвали","title_en":"Zhinvali"},{"id":2400553,"title_ru":"Жинота","title_en":"Zhinota"},{"id":5470301,"title_ru":"Закви","title_en":"Zakvi"},{"id":2400432,"title_ru":"Заридзееби","title_en":"Zaridzeebi"},{"id":2400015,"title_ru":"Звандрипш","title_en":"Zvandripsh"},{"id":2400495,"title_ru":"Зеда-Агви","title_en":"Zeda-Agvi"},{"id":2400173,"title_ru":"Зеда-Баши","title_en":"Zeda-Bashi"},{"id":2400174,"title_ru":"Зеда-Бзвани","title_en":"Zeda-Bzvani"},{"id":2400655,"title_ru":"Зеда-Вардзиа","title_en":"Zeda-Vardzia"},{"id":1937503,"title_ru":"Зеда-Сазано","title_en":"Zeda-Sazano"},{"id":5471889,"title_ru":"Зеда-Эцери","title_en":"Zeda-Etseri"},{"id":2400175,"title_ru":"Зедубани","title_en":"Zedubani"},{"id":2400433,"title_ru":"Зейстечо","title_en":"Zeystecho"},{"id":2400176,"title_ru":"Зекари","title_en":"Zekari"},{"id":1970456,"title_ru":"Земо Баргеби","title_en":"Zemo Bargebi"},{"id":2400496,"title_ru":"Земо Бари","title_en":"Zemo Bari"},{"id":1909304,"title_ru":"Земо-Алвани","title_en":"Zemo-Alvani"},{"id":2400554,"title_ru":"Земо-Биа","title_en":"Zemo-Bia"},{"id":2400434,"title_ru":"Земо-Боли","title_en":"Zemo-Boli"},{"id":2400704,"title_ru":"Земо-Занкари","title_en":"Zemo-Zankari"},{"id":5479437,"title_ru":"Земо-Орозмани","title_en":"Zemo-Orozmani"},{"id":2400705,"title_ru":"Земо-Рока","title_en":"Zemo-Roka"},{"id":2400101,"title_ru":"Земохети","title_en":"Zemokheti"},{"id":1973310,"title_ru":"Зестафони","title_en":"Zestafoni"},{"id":1935755,"title_ru":"Зесхо","title_en":"Zeskho"},{"id":2400362,"title_ru":"Зирбити","title_en":"Zirbiti"},{"id":1965558,"title_ru":"Знаури","title_en":"Znauri"},{"id":2400497,"title_ru":"Зуби","title_en":"Zubi"},{"id":2400498,"title_ru":"Зуби","title_en":"Zubi"},{"id":2400556,"title_ru":"Зуби","title_en":"Zubi"},{"id":1951841,"title_ru":"Зугдиди","title_en":"Zugdidi"},{"id":2400049,"title_ru":"Зундага","title_en":"Zundaga"},{"id":2400363,"title_ru":"Иакубло","title_en":"Iakublo"},{"id":2400102,"title_ru":"Ианети","title_en":"Ianeti"},{"id":5470298,"title_ru":"Икалто","title_en":"Ikalto"},{"id":2400706,"title_ru":"Иквневи","title_en":"Ikvnevi"},{"id":2400435,"title_ru":"Икети","title_en":"Iketi"},{"id":2400016,"title_ru":"Илор","title_en":"Ilor"},{"id":1954229,"title_ru":"Имера","title_en":"Imera"},{"id":2400154,"title_ru":"Имеретинский","title_en":"Imeretinsky"},{"id":2400364,"title_ru":"Имири","title_en":"Imiri"},{"id":2400707,"title_ru":"Инаури","title_en":"Inauri"},{"id":5470326,"title_ru":"Ингири","title_en":"Ingiri"},{"id":2400103,"title_ru":"Интабуэти","title_en":"Intabueti"},{"id":5471191,"title_ru":"Иормуганло","title_en":"Iormuganlo"},{"id":2400366,"title_ru":"Ипнари","title_en":"Ipnari"},{"id":2400558,"title_ru":"Ипрари","title_en":"Iprari"},{"id":2400367,"title_ru":"Ирганчай","title_en":"Irganchay"},{"id":2400559,"title_ru":"Исула","title_en":"Isula"},{"id":5470353,"title_ru":"Кабали","title_en":"Kabali"},{"id":2400403,"title_ru":"Кавта ","title_en":"Kavta "},{"id":1926203,"title_ru":"Казбеги","title_en":"Kazbegi"},{"id":21703,"title_ru":"Казрети","title_en":"Kazreti"},{"id":1923039,"title_ru":"Калдахуара","title_en":"Kaldakhuara"},{"id":2400368,"title_ru":"Калинино","title_en":"Kalinino"},{"id":2400369,"title_ru":"Калиновка","title_en":"Kalinovka"},{"id":2400018,"title_ru":"Каманы","title_en":"Kamany"},{"id":2400370,"title_ru":"Камарло","title_en":"Kamarlo"},{"id":2400437,"title_ru":"Каноби","title_en":"Kanobi"},{"id":5470357,"title_ru":"Капанахчи","title_en":"Kapanakhchi"},{"id":2400708,"title_ru":"Капрашиани","title_en":"Kaprashiani"},{"id":2400709,"title_ru":"Карагаджи","title_en":"Karagadzhi"},{"id":5422757,"title_ru":"Караджала","title_en":"Karadzhala"},{"id":1915719,"title_ru":"Караком","title_en":"Karakom"},{"id":5470328,"title_ru":"Каралети","title_en":"Karaleti"},{"id":2400710,"title_ru":"Карели","title_en":"Kareli"},{"id":2400560,"title_ru":"Кари","title_en":"Kari"},{"id":2400656,"title_ru":"Картиками","title_en":"Kartikami"},{"id":2400657,"title_ru":"Карцахи","title_en":"Kartsakhi"},{"id":1916552,"title_ru":"Каспи","title_en":"Kaspi"},{"id":2400050,"title_ru":"Кахабери","title_en":"Kakhaberi"},{"id":5470325,"title_ru":"Кахати","title_en":"Kakhati"},{"id":1927460,"title_ru":"Кахетинский","title_en":"Kakhetinsky"},{"id":2400438,"title_ru":"Кацалхеви","title_en":"Katsalkhevi"},{"id":5471891,"title_ru":"Качагани","title_en":"Kachagani"},{"id":2400104,"title_ru":"Квабга","title_en":"Kvabga"},{"id":2400178,"title_ru":"Квадаура","title_en":"Kvadaura"},{"id":22662,"title_ru":"Квайса","title_en":"Kvaysa"},{"id":1903600,"title_ru":"Кварели","title_en":"Kvareli"},{"id":2400712,"title_ru":"Кватетри","title_en":"Kvatetri"},{"id":2400499,"title_ru":"Квашхиети","title_en":"Kvashkhieti"},{"id":2400179,"title_ru":"Кведа-Беретиса","title_en":"Kveda-Beretisa"},{"id":2400180,"title_ru":"Кведа-Зегани","title_en":"Kveda-Zegani"},{"id":2400181,"title_ru":"Кведа-Оргули","title_en":"Kveda-Orguli"},{"id":2400561,"title_ru":"Кведа-Сорта","title_en":"Kveda-Sorta"},{"id":2400371,"title_ru":"Квемо-Ахкалапа","title_en":"Kvemo-Akhkalapa"},{"id":2400337,"title_ru":"Квемо-Картлийский","title_en":"Kvemo-Kartliysky"},{"id":5421590,"title_ru":"Квемо-Кеди","title_en":"Kvemo-Kedi"},{"id":2400105,"title_ru":"Квемо-Макванети","title_en":"Kvemo-Makvaneti"},{"id":2400439,"title_ru":"Квемо-Млети","title_en":"Kvemo-Mleti"},{"id":2400182,"title_ru":"Квемо-Нагвазаво","title_en":"Kvemo-Nagvazavo"},{"id":2400106,"title_ru":"Квемо-Натанеби","title_en":"Kvemo-Natanebi"},{"id":2400713,"title_ru":"Квемо-Ничбиси","title_en":"Kvemo-Nichbisi"},{"id":2400714,"title_ru":"Квемо-Отреви","title_en":"Kvemo-Otrevi"},{"id":2400715,"title_ru":"Квемо-Рока","title_en":"Kvemo-Roka"},{"id":2400716,"title_ru":"Квемо-Собиси","title_en":"Kvemo-Sobisi"},{"id":5470299,"title_ru":"Квемо-Ходашени","title_en":"Kvemo-Khodasheni"},{"id":2400440,"title_ru":"Квемо-Шуахеви","title_en":"Kvemo-Shuakhevi"},{"id":2400107,"title_ru":"Квемо-Шухути","title_en":"Kvemo-Shukhuti"},{"id":2400108,"title_ru":"Квенобани","title_en":"Kvenobani"},{"id":2400372,"title_ru":"Квесети","title_en":"Kveseti"},{"id":2400441,"title_ru":"Квириасхеви","title_en":"Kviriaskhevi"},{"id":5479329,"title_ru":"Квитири","title_en":"Kvitiri"},{"id":5470339,"title_ru":"Кеда","title_en":"Keda"},{"id":1946489,"title_ru":"Келасури","title_en":"Kelasuri"},{"id":2400442,"title_ru":"Кенчаклде","title_en":"Kenchaklde"},{"id":5471886,"title_ru":"Кесало","title_en":"Kesalo"},{"id":1956338,"title_ru":"Кизил Килиса","title_en":"Kizil Kilisa"},{"id":2400717,"title_ru":"Киндзати","title_en":"Kindzati"},{"id":2400051,"title_ru":"Кинкиша","title_en":"Kinkisha"},{"id":2400443,"title_ru":"Кинта","title_en":"Kinta"},{"id":5470340,"title_ru":"Кинчаури","title_en":"Kinchauri"},{"id":2400373,"title_ru":"Кирихло","title_en":"Kirikhlo"},{"id":2400500,"title_ru":"Кирови","title_en":"Kirovi"},{"id":2400374,"title_ru":"Кировиси","title_en":"Kirovisi"},{"id":2400658,"title_ru":"Кисатиби","title_en":"Kisatibi"},{"id":2400444,"title_ru":"Кишхеви","title_en":"Kishkhevi"},{"id":2400659,"title_ru":"Клде","title_en":"Klde"},{"id":2400109,"title_ru":"Кнчкати","title_en":"Knchkati"},{"id":2400052,"title_ru":"Кобалаури","title_en":"Kobalauri"},{"id":1955484,"title_ru":"Кобулети","title_en":"Kobuleti"},{"id":1927473,"title_ru":"Кода","title_en":"Koda"},{"id":1937170,"title_ru":"Коджори","title_en":"Kodzhori"},{"id":2400183,"title_ru":"Кокасцкали","title_en":"Kokastskali"},{"id":2400562,"title_ru":"Коко","title_en":"Koko"},{"id":5470329,"title_ru":"Колхида (Псахара)","title_en":"Kolkhida (psakhara)"},{"id":5470318,"title_ru":"Кончкати","title_en":"Konchkati"},{"id":1908565,"title_ru":"Копитнари","title_en":"Kopitnari"},{"id":2400718,"title_ru":"Корниси","title_en":"Kornisi"},{"id":2400054,"title_ru":"Королистави","title_en":"Korolistavi"},{"id":2400719,"title_ru":"Корсеви","title_en":"Korsevi"},{"id":2400563,"title_ru":"Корулд","title_en":"Koruld"},{"id":5470302,"title_ru":"Корхи","title_en":"Korkhi"},{"id":2400445,"title_ru":"Косели","title_en":"Koseli"},{"id":2400720,"title_ru":"Котанто","title_en":"Kotanto"},{"id":2400110,"title_ru":"Кохнари","title_en":"Kokhnari"},{"id":2400721,"title_ru":"Кошкеби","title_en":"Koshkebi"},{"id":2400446,"title_ru":"Кудо","title_en":"Kudo"},{"id":2400447,"title_ru":"Кудро","title_en":"Kudro"},{"id":1706864,"title_ru":"Кулаш","title_en":"Kulash"},{"id":5470305,"title_ru":"Куликами","title_en":"Kulikami"},{"id":5470358,"title_ru":"Куллари","title_en":"Kullari"},{"id":1907139,"title_ru":"Кумиси","title_en":"Kumisi"},{"id":1965594,"title_ru":"Курта","title_en":"Kurta"},{"id":3631,"title_ru":"Кутаиси","title_en":"Kutaisi"},{"id":1905675,"title_ru":"Кутол","title_en":"Kutol"},{"id":2400185,"title_ru":"Кушубаури","title_en":"Kushubauri"},{"id":2400378,"title_ru":"Кушчи","title_en":"Kushchi"},{"id":5470362,"title_ru":"Кущи","title_en":"Kuschi"},{"id":1904586,"title_ru":"Кындыг","title_en":"Kyndyg"},{"id":1961716,"title_ru":"Лабра","title_en":"Labra"},{"id":20644,"title_ru":"Лагодехи","title_en":"Lagodekhi"},{"id":1901746,"title_ru":"Лаитури","title_en":"Laituri"},{"id":2400501,"title_ru":"Лайлаши","title_en":"Laylashi"},{"id":2400574,"title_ru":"Лалхорали ","title_en":"Lalkhorali "},{"id":1945749,"title_ru":"Ланчхути","title_en":"Lanchkhuti"},{"id":2400448,"title_ru":"Лапанаанткари","title_en":"Lapanaantkari"},{"id":2400564,"title_ru":"Лара","title_en":"Lara"},{"id":2400502,"title_ru":"Ларчвали","title_en":"Larchvali"},{"id":2400503,"title_ru":"Ласуриаши","title_en":"Lasuriashi"},{"id":2400565,"title_ru":"Лахамула","title_en":"Lakhamula"},{"id":2400566,"title_ru":"Лахаши","title_en":"Lakhashi"},{"id":2400567,"title_ru":"Лахушди","title_en":"Lakhushdi"},{"id":2400568,"title_ru":"Легахаре","title_en":"Legakhare"},{"id":2400569,"title_ru":"Лекалмахи","title_en":"Lekalmakhi"},{"id":2400570,"title_ru":"Лекарде","title_en":"Lekarde"},{"id":2400571,"title_ru":"Лекосанди","title_en":"Lekosandi"},{"id":2400379,"title_ru":"Лениниси","title_en":"Leninisi"},{"id":2400504,"title_ru":"Лентехи","title_en":"Lentekhi"},{"id":2400572,"title_ru":"Лентехи","title_en":"Lentekhi"},{"id":2400113,"title_ru":"Леса","title_en":"Lesa"},{"id":1936239,"title_ru":"Леселидзе","title_en":"Leselidze"},{"id":2400573,"title_ru":"Лесичине","title_en":"Lesichine"},{"id":2400186,"title_ru":"Лехидристави","title_en":"Lekhidristavi"},{"id":1923756,"title_ru":"Лиа","title_en":"Lia"},{"id":1962053,"title_ru":"Ливад","title_en":"Livad"},{"id":1916994,"title_ru":"Лидзава","title_en":"Lidzava"},{"id":2400114,"title_ru":"Лихаури","title_en":"Likhauri"},{"id":2400505,"title_ru":"Лихети","title_en":"Likheti"},{"id":2400449,"title_ru":"Лишо","title_en":"Lisho"},{"id":2400723,"title_ru":"Ломиси","title_en":"Lomisi"},{"id":2400020,"title_ru":"Лыхны","title_en":"Lykhny"},{"id":2400187,"title_ru":"Маглаки","title_en":"Maglaki"},{"id":2400450,"title_ru":"Маграни","title_en":"Magrani"},{"id":2400115,"title_ru":"Макванети","title_en":"Makvaneti"},{"id":2400116,"title_ru":"Мамати","title_en":"Mamati"},{"id":2400575,"title_ru":"Мами","title_en":"Mami"},{"id":2202503,"title_ru":"Мамцвара","title_en":"Mamtsvara"},{"id":1517651,"title_ru":"Манглиси","title_en":"Manglisi"},{"id":2400055,"title_ru":"Марадиди","title_en":"Maradidi"},{"id":1969145,"title_ru":"Марнеули","title_en":"Marneuli"},{"id":1965604,"title_ru":"Мартвили","title_en":"Martvili"},{"id":5470345,"title_ru":"Марткопи","title_en":"Martkopi"},{"id":1706626,"title_ru":"Махинджаури","title_en":"Makhindzhauri"},{"id":2400057,"title_ru":"Махунцети","title_en":"Makhuntseti"},{"id":1969210,"title_ru":"Мачара","title_en":"Machara"},{"id":5470308,"title_ru":"Мачатиа","title_en":"Machatia"},{"id":2400724,"title_ru":"Мгебриани","title_en":"Mgebriani"},{"id":2400577,"title_ru":"Медани","title_en":"Medani"},{"id":2400058,"title_ru":"Мекейдзейеби","title_en":"Mekeydzeyebi"},{"id":2400188,"title_ru":"Мелаури","title_en":"Melauri"},{"id":2400117,"title_ru":"Мелекедури","title_en":"Melekeduri"},{"id":2400118,"title_ru":"Меоре-Балда","title_en":"Meore-Balda"},{"id":2400578,"title_ru":"Меоре-Гурипули","title_en":"Meore-Guripuli"},{"id":5470327,"title_ru":"Мерети","title_en":"Mereti"},{"id":1915349,"title_ru":"Мериа","title_en":"Meria"},{"id":22695,"title_ru":"Мерхеул","title_en":"Merkheul"},{"id":1707529,"title_ru":"Местиа","title_en":"Mestia"},{"id":2400451,"title_ru":"Микелиани","title_en":"Mikeliani"},{"id":2400452,"title_ru":"Мисакциели","title_en":"Misaktsieli"},{"id":1950607,"title_ru":"Моква","title_en":"Mokva"},{"id":2400660,"title_ru":"Молити","title_en":"Moliti"},{"id":2400580,"title_ru":"Монгири","title_en":"Mongiri"},{"id":1965603,"title_ru":"Мохиси","title_en":"Mokhisi"},{"id":2400453,"title_ru":"Моцмао","title_en":"Motsmao"},{"id":2400189,"title_ru":"Мтисдзири","title_en":"Mtisdziri"},{"id":2400120,"title_ru":"Мтиспири","title_en":"Mtispiri"},{"id":2400661,"title_ru":"Мугарети","title_en":"Mugareti"},{"id":2400454,"title_ru":"Мугуда","title_en":"Muguda"},{"id":2400581,"title_ru":"Мужава","title_en":"Muzhava"},{"id":5422758,"title_ru":"Мукузани","title_en":"Mukuzani"},{"id":2400725,"title_ru":"Мулдарта","title_en":"Muldarta"},{"id":2400582,"title_ru":"Мунцква","title_en":"Muntskva"},{"id":2400662,"title_ru":"Мурджахети","title_en":"Murdzhakheti"},{"id":2400583,"title_ru":"Муршкели","title_en":"Murshkeli"},{"id":2400726,"title_ru":"Мухаури","title_en":"Mukhauri"},{"id":5471729,"title_ru":"Мухаэстате","title_en":"Mukhaestate"},{"id":2400584,"title_ru":"Муцди","title_en":"Mutsdi"},{"id":5479494,"title_ru":"Мцара","title_en":"Mtsara"},{"id":2400455,"title_ru":"Мцитуреби","title_en":"Mtsiturebi"},{"id":1802445,"title_ru":"Мцхета","title_en":"Mtskheta"},{"id":2400407,"title_ru":"Мцхета-Мтианетский","title_en":"Mtskheta-Mtianetsky"},{"id":2400663,"title_ru":"Мясникиари","title_en":"Myasnikiari"},{"id":2400727,"title_ru":"Набахтеви","title_en":"Nabakhtevi"},{"id":2400121,"title_ru":"Набеглави","title_en":"Nabeglavi"},{"id":2400190,"title_ru":"Набослеви","title_en":"Naboslevi"},{"id":2400382,"title_ru":"Навтиани","title_en":"Navtiani"},{"id":2400059,"title_ru":"Нагвареви","title_en":"Nagvarevi"},{"id":2400122,"title_ru":"Нагомари","title_en":"Nagomari"},{"id":2400728,"title_ru":"Нагутни","title_en":"Nagutni"},{"id":2400457,"title_ru":"Надабури","title_en":"Nadaburi"},{"id":2400383,"title_ru":"Назарло","title_en":"Nazarlo"},{"id":5469348,"title_ru":"Накиани","title_en":"Nakiani"},{"id":2400585,"title_ru":"Накипари","title_en":"Nakipari"},{"id":2400506,"title_ru":"Накуралеши","title_en":"Nakuraleshi"},{"id":2400191,"title_ru":"Налепсаво","title_en":"Nalepsavo"},{"id":2400507,"title_ru":"Наманеви","title_en":"Namanevi"},{"id":2400458,"title_ru":"Наоза","title_en":"Naoza"},{"id":1913863,"title_ru":"Наохреби","title_en":"Naokhrebi"},{"id":5470324,"title_ru":"Наразени","title_en":"Narazeni"},{"id":5470363,"title_ru":"Нардевани","title_en":"Nardevani"},{"id":2400123,"title_ru":"Наруджа","title_en":"Narudzha"},{"id":2400124,"title_ru":"Насакирали","title_en":"Nasakirali"},{"id":2400125,"title_ru":"Натанеби","title_en":"Natanebi"},{"id":2400192,"title_ru":"Нахаребаво","title_en":"Nakharebavo"},{"id":5471192,"title_ru":"Нахидури","title_en":"Nakhiduri"},{"id":2400586,"title_ru":"Нацулуку","title_en":"Natsuluku"},{"id":2400587,"title_ru":"Начкаду","title_en":"Nachkadu"},{"id":2400126,"title_ru":"Нигоиты","title_en":"Nigoity"},{"id":2400729,"title_ru":"Нижние Сочи","title_en":"Nizhnie Sochi"},{"id":1911434,"title_ru":"Нижние Эшеры","title_en":"Nizhnie Eshery"},{"id":5470311,"title_ru":"Нижний Мерхеул (Квемо-Мерхеули)","title_en":"Nizhny Merkheul (kvemo-Merkheuli)"},{"id":2400508,"title_ru":"Никорцминда","title_en":"Nikortsminda"},{"id":2400664,"title_ru":"Ниноцминда","title_en":"Ninotsminda"},{"id":1961162,"title_ru":"Новый Афон","title_en":"Novy Afon"},{"id":2400730,"title_ru":"Нули","title_en":"Nuli"},{"id":1901793,"title_ru":"Озургети","title_en":"Ozurgeti"},{"id":2400588,"title_ru":"Октомбери","title_en":"Oktomberi"},{"id":1909146,"title_ru":"Окуми","title_en":"Okumi"},{"id":2400509,"title_ru":"Окуреши","title_en":"Okureshi"},{"id":5470309,"title_ru":"Олаверди","title_en":"Olaverdi"},{"id":2400731,"title_ru":"Олози","title_en":"Olozi"},{"id":2400510,"title_ru":"Они","title_en":"Oni"},{"id":1931093,"title_ru":"Опрети","title_en":"Opreti"},{"id":2400128,"title_ru":"Орагве","title_en":"Oragve"},{"id":2400511,"title_ru":"Орбели","title_en":"Orbeli"},{"id":2400665,"title_ru":"Оргора","title_en":"Orgora"},{"id":2400589,"title_ru":"Орджоникидзе","title_en":"Ordzhonikidze"},{"id":5471635,"title_ru":"Ороджолори","title_en":"Orodzholori"},{"id":2400193,"title_ru":"Орхви","title_en":"Orkhvi"},{"id":2400060,"title_ru":"Орцва","title_en":"Ortsva"},{"id":2400194,"title_ru":"Осунела","title_en":"Osunela"},{"id":2400666,"title_ru":"Ота","title_en":"Ota"},{"id":5470300,"title_ru":"Отхара","title_en":"Otkhara"},{"id":1941587,"title_ru":"Очамчира","title_en":"Ochamchira"},{"id":1908374,"title_ru":"Очхамури","title_en":"Ochkhamuri"},{"id":2400590,"title_ru":"Панага","title_en":"Panaga"},{"id":2400385,"title_ru":"Пантиани","title_en":"Pantiani"},{"id":1706882,"title_ru":"Парцханаканеби","title_en":"Partskhanakanebi"},{"id":2400129,"title_ru":"Парцхма","title_en":"Partskhma"},{"id":2400195,"title_ru":"Патара-Гантиади","title_en":"Patara-Gantiadi"},{"id":2400196,"title_ru":"Патара-Голиси","title_en":"Patara-Golisi"},{"id":2400386,"title_ru":"Патара-Дманиси","title_en":"Patara-Dmanisi"},{"id":5470332,"title_ru":"Патара-Памачи","title_en":"Patara-Pamachi"},{"id":2400591,"title_ru":"Патара-Поти","title_en":"Patara-Poti"},{"id":2400732,"title_ru":"Патара-Церети","title_en":"Patara-Tsereti"},{"id":2400733,"title_ru":"Пели","title_en":"Peli"},{"id":2400512,"title_ru":"Пипилети","title_en":"Pipileti"},{"id":2400592,"title_ru":"Пирвели Маиси","title_en":"Pirveli Maisi"},{"id":1968468,"title_ru":"Пицунда","title_en":"Pitsunda"},{"id":2400130,"title_ru":"Пичвнари","title_en":"Pichvnari"},{"id":1967003,"title_ru":"Поти","title_en":"Poti"},{"id":2400594,"title_ru":"Поцхо","title_en":"Potskho"},{"id":2400513,"title_ru":"Привели-Тола","title_en":"Priveli-Tola"},{"id":2400459,"title_ru":"Придонаанткари","title_en":"Pridonaantkari"},{"id":1936134,"title_ru":"Приморский","title_en":"Primorsky"},{"id":2400026,"title_ru":"Псху","title_en":"Pskhu"},{"id":2400460,"title_ru":"Пхундави","title_en":"Pkhundavi"},{"id":2400734,"title_ru":"Раро","title_en":"Raro"},{"id":2400483,"title_ru":"Рача-Лечхумский и Квемо-Сванетский","title_en":"Racha-Lechkhumsky I Kvemo-Svanetsky"},{"id":2400197,"title_ru":"Ргани","title_en":"Rgani"},{"id":2400735,"title_ru":"Ргваличала","title_en":"Rgvalichala"},{"id":2400595,"title_ru":"Река","title_en":"Reka"},{"id":5470322,"title_ru":"Рике","title_en":"Rike"},{"id":2400061,"title_ru":"Рикети","title_en":"Riketi"},{"id":1953178,"title_ru":"Рустави","title_en":"Rustavi"},{"id":1971126,"title_ru":"Рухи","title_en":"Rukhi"},{"id":2400514,"title_ru":"Рцхмелури","title_en":"Rtskhmeluri"},{"id":2400597,"title_ru":"Сабажо","title_en":"Sabazho"},{"id":2400461,"title_ru":"Сабарклети","title_en":"Sabarkleti"},{"id":1705973,"title_ru":"Саберио","title_en":"Saberio"},{"id":2400667,"title_ru":"Сагамо","title_en":"Sagamo"},{"id":1517066,"title_ru":"Сагареджо","title_en":"Sagaredzho"},{"id":5470663,"title_ru":"Садахло","title_en":"Sadakhlo"},{"id":2400388,"title_ru":"Саджа","title_en":"Sadzha"},{"id":1970180,"title_ru":"Саджавахо","title_en":"Sadzhavakho"},{"id":2400668,"title_ru":"Саджиа","title_en":"Sadzhia"},{"id":2400462,"title_ru":"Садзегури-Пирвели","title_en":"Sadzeguri-Pirveli"},{"id":5470333,"title_ru":"Садзели","title_en":"Sadzeli"},{"id":2400515,"title_ru":"Садмели","title_en":"Sadmeli"},{"id":2400736,"title_ru":"Сакашети","title_en":"Sakasheti"},{"id":2400669,"title_ru":"Сакире","title_en":"Sakire"},{"id":2400598,"title_ru":"Сакирио","title_en":"Sakirio"},{"id":2400670,"title_ru":"Сакудабели","title_en":"Sakudabeli"},{"id":2400516,"title_ru":"Салетодиано","title_en":"Saletodiano"},{"id":2400542,"title_ru":"Самегрело и Земо-Сванетский","title_en":"Samegrelo I Zemo-Svanetsky"},{"id":2400062,"title_ru":"Самолети","title_en":"Samoleti"},{"id":2400737,"title_ru":"Самочала","title_en":"Samochala"},{"id":1974697,"title_ru":"Самтредиа","title_en":"Samtredia"},{"id":2400357,"title_ru":"Самтредо","title_en":"Samtredo"},{"id":2400738,"title_ru":"Самцериси","title_en":"Samtserisi"},{"id":2400621,"title_ru":"Самцхе-Джавахетский","title_en":"Samtskhe-Dzhavakhetsky"},{"id":2400199,"title_ru":"Сарбеви","title_en":"Sarbevi"},{"id":2400739,"title_ru":"Саритата","title_en":"Saritata"},{"id":5470348,"title_ru":"Саркинети","title_en":"Sarkineti"},{"id":1906167,"title_ru":"Сартичала","title_en":"Sartichala"},{"id":2400463,"title_ru":"Сасадило","title_en":"Sasadilo"},{"id":2400740,"title_ru":"Сасирети","title_en":"Sasireti"},{"id":2400741,"title_ru":"Сативе","title_en":"Sative"},{"id":2400742,"title_ru":"Сатовле","title_en":"Satovle"},{"id":2400200,"title_ru":"Сахулари","title_en":"Sakhulari"},{"id":2400063,"title_ru":"Сацховрия","title_en":"Satskhovria"},{"id":2400131,"title_ru":"Сачамисери","title_en":"Sachamiseri"},{"id":2400201,"title_ru":"Сачхере","title_en":"Sachkhere"},{"id":2400202,"title_ru":"Свери","title_en":"Sveri"},{"id":2400599,"title_ru":"Сгуриши","title_en":"Sgurishi"},{"id":1931304,"title_ru":"Сенаки","title_en":"Senaki"},{"id":2400517,"title_ru":"Сеубани","title_en":"Seubani"},{"id":1516200,"title_ru":"Сигнахи","title_en":"Signakhi"},{"id":2400203,"title_ru":"Сиктарва","title_en":"Siktarva"},{"id":2400132,"title_ru":"Силаури","title_en":"Silauri"},{"id":2400064,"title_ru":"Силибаури","title_en":"Silibauri"},{"id":2400204,"title_ru":"Симонети","title_en":"Simoneti"},{"id":2400389,"title_ru":"Сиони","title_en":"Sioni"},{"id":2400133,"title_ru":"Сириачкони","title_en":"Siriachkoni"},{"id":2400464,"title_ru":"Сно","title_en":"Sno"},{"id":2400390,"title_ru":"Согутло","title_en":"Sogutlo"},{"id":2400518,"title_ru":"Сори","title_en":"Sori"},{"id":2400205,"title_ru":"Сормони","title_en":"Sormoni"},{"id":2400671,"title_ru":"Сулда","title_en":"Sulda"},{"id":2400134,"title_ru":"Супса","title_en":"Supsa"},{"id":1715185,"title_ru":"Сурами","title_en":"Surami"},{"id":2400135,"title_ru":"Суреби","title_en":"Surebi"},{"id":1969977,"title_ru":"Сухуми \/ Сухум","title_en":"Sukhumi"},{"id":2400465,"title_ru":"Схалтба","title_en":"Skhaltba"},{"id":5470334,"title_ru":"Схвилиси","title_en":"Skhvilisi"},{"id":2400391,"title_ru":"Табаруки","title_en":"Tabaruki"},{"id":2400136,"title_ru":"Тавпанта","title_en":"Tavpanta"},{"id":1709954,"title_ru":"Таглан","title_en":"Taglan"},{"id":2400065,"title_ru":"Таго","title_en":"Tago"},{"id":2400392,"title_ru":"Тазакенди","title_en":"Tazakendi"},{"id":2400398,"title_ru":"Талавери (Фахрало)","title_en":"Talaveri (fakhralo)"},{"id":2400744,"title_ru":"Тами","title_en":"Tami"},{"id":1937891,"title_ru":"Тамыш","title_en":"Tamysh"},{"id":2400393,"title_ru":"Тандзиа","title_en":"Tandzia"},{"id":2400466,"title_ru":"Тбети","title_en":"Tbeti"},{"id":1965294,"title_ru":"Тбилиси","title_en":"Tbilisi"},{"id":2400394,"title_ru":"Теджиси","title_en":"Tedzhisi"},{"id":2400519,"title_ru":"Текали","title_en":"Tekali"},{"id":14445,"title_ru":"Телави","title_en":"Telavi"},{"id":1975396,"title_ru":"Терджола","title_en":"Terdzhola"},{"id":1262,"title_ru":"Тетрицкаро","title_en":"Tetritskaro"},{"id":2400467,"title_ru":"Тианети","title_en":"Tianeti"},{"id":5470350,"title_ru":"Тиви","title_en":"Tivi"},{"id":2400745,"title_ru":"Тигви","title_en":"Tigvi"},{"id":5470364,"title_ru":"Тикилиса","title_en":"Tikilisa"},{"id":2400746,"title_ru":"Тинисхиди","title_en":"Tiniskhidi"},{"id":2400601,"title_ru":"Тита","title_en":"Tita"},{"id":2400207,"title_ru":"Ткачири","title_en":"Tkachiri"},{"id":1293,"title_ru":"Ткварчели","title_en":"Tkvarcheli"},{"id":2400208,"title_ru":"Ткемлована","title_en":"Tkemlovana"},{"id":11273,"title_ru":"Ткибули","title_en":"Tkibuli"},{"id":2400396,"title_ru":"Ткиспири","title_en":"Tkispiri"},{"id":2400137,"title_ru":"Тобахча-Тавсуреби","title_en":"Tobakhcha-Tavsurebi"},{"id":2400602,"title_ru":"Токлулар","title_en":"Toklular"},{"id":2400672,"title_ru":"Толоши","title_en":"Toloshi"},{"id":2400673,"title_ru":"Тори","title_en":"Tori"},{"id":2400603,"title_ru":"Тотани","title_en":"Totani"},{"id":1911181,"title_ru":"Триалети","title_en":"Trialeti"},{"id":5470310,"title_ru":"Турцхи","title_en":"Turtskhi"},{"id":2400066,"title_ru":"Тхилвана","title_en":"Tkhilvana"},{"id":2400030,"title_ru":"Тхина","title_en":"Tkhina"},{"id":2400138,"title_ru":"Тхинвали","title_en":"Tkhinvali"},{"id":1909414,"title_ru":"Уджарма","title_en":"Udzharma"},{"id":2400468,"title_ru":"Уканапшави","title_en":"Ukanapshavi"},{"id":2400469,"title_ru":"Уканахо","title_en":"Ukanakho"},{"id":2400747,"title_ru":"Улумба","title_en":"Ulumba"},{"id":1971716,"title_ru":"Ульяновка","title_en":"Ulyanovka"},{"id":2400520,"title_ru":"Урави","title_en":"Uravi"},{"id":2400748,"title_ru":"Урбниси","title_en":"Urbnisi"},{"id":1962741,"title_ru":"Уреки","title_en":"Ureki"},{"id":2400067,"title_ru":"Урехи","title_en":"Urekhi"},{"id":2400210,"title_ru":"Усахело","title_en":"Usakhelo"},{"id":2400521,"title_ru":"Усахело","title_en":"Usakhelo"},{"id":2400211,"title_ru":"Ухути","title_en":"Ukhuti"},{"id":2400522,"title_ru":"Уцера","title_en":"Utsera"},{"id":2400604,"title_ru":"Ушапати","title_en":"Ushapati"},{"id":2400605,"title_ru":"Ушкванари","title_en":"Ushkvanari"},{"id":2400523,"title_ru":"Фарахети","title_en":"Farakheti"},{"id":2400140,"title_ru":"Хаджалия","title_en":"Khadzhalia"},{"id":2400470,"title_ru":"Хаишо","title_en":"Khaisho"},{"id":2400068,"title_ru":"Хала","title_en":"Khala"},{"id":1922571,"title_ru":"Хандо","title_en":"Khando"},{"id":2400212,"title_ru":"Харагаули","title_en":"Kharagauli"},{"id":2400471,"title_ru":"Харбали","title_en":"Kharbali"},{"id":2400675,"title_ru":"Харджами","title_en":"Khardzhami"},{"id":2400472,"title_ru":"Хартишо","title_en":"Khartisho"},{"id":2400473,"title_ru":"Хахабо","title_en":"Khakhabo"},{"id":5470365,"title_ru":"Хачкои","title_en":"Khachkoi"},{"id":1951990,"title_ru":"Хашури","title_en":"Khashuri"},{"id":2400213,"title_ru":"Хвашити","title_en":"Khvashiti"},{"id":2400141,"title_ru":"Хеви","title_en":"Khevi"},{"id":5470330,"title_ru":"Хеивани (Амзара)","title_en":"Kheivani (amzara)"},{"id":1941635,"title_ru":"Хелвачаури","title_en":"Khelvachauri"},{"id":2400524,"title_ru":"Хеледи","title_en":"Kheledi"},{"id":2400750,"title_ru":"Хеоба","title_en":"Kheoba"},{"id":2400606,"title_ru":"Хецера","title_en":"Khetsera"},{"id":2400214,"title_ru":"Хидари","title_en":"Khidari"},{"id":2400751,"title_ru":"Хидискури","title_en":"Khidiskuri"},{"id":2400142,"title_ru":"Хидистави","title_en":"Khidistavi"},{"id":2400752,"title_ru":"Хидистави","title_en":"Khidistavi"},{"id":1907015,"title_ru":"Хичаури","title_en":"Khichauri"},{"id":1903378,"title_ru":"Хоби","title_en":"Khobi"},{"id":2400753,"title_ru":"Ходз","title_en":"Khodz"},{"id":2400215,"title_ru":"Хомули","title_en":"Khomuli"},{"id":1918725,"title_ru":"Хони","title_en":"Khoni"},{"id":2400399,"title_ru":"Хопист","title_en":"Khopist"},{"id":2400525,"title_ru":"Хотеви","title_en":"Khotevi"},{"id":2400526,"title_ru":"Хофури","title_en":"Khofuri"},{"id":2400031,"title_ru":"Хуап","title_en":"Khuap"},{"id":1965505,"title_ru":"Хульгумо","title_en":"Khulgumo"},{"id":1929437,"title_ru":"Хумушкури","title_en":"Khumushkuri"},{"id":2400217,"title_ru":"Хунджулоури","title_en":"Khundzhulouri"},{"id":2400069,"title_ru":"Хуцубани","title_en":"Khutsubani"},{"id":5469989,"title_ru":"Хыпста","title_en":"Khypsta"},{"id":2400754,"title_ru":"Цагат-Шипран","title_en":"Tsagat-Shipran"},{"id":1715247,"title_ru":"Цагвери","title_en":"Tsagveri"},{"id":2400527,"title_ru":"Цагери","title_en":"Tsageri"},{"id":2400608,"title_ru":"Цалдаши","title_en":"Tsaldashi"},{"id":1518993,"title_ru":"Цаленджиха","title_en":"Tsalendzhikha"},{"id":1705151,"title_ru":"Цалка","title_en":"Tsalka"},{"id":2400528,"title_ru":"Цана","title_en":"Tsana"},{"id":2400610,"title_ru":"Цана","title_en":"Tsana"},{"id":1918386,"title_ru":"Цандрыпш (Гантиади)","title_en":"Tsandrypsh (gantiadi)"},{"id":1929825,"title_ru":"Царче","title_en":"Tsarche"},{"id":2400218,"title_ru":"Цасри","title_en":"Tsasri"},{"id":2400529,"title_ru":"Цахи","title_en":"Tsakhi"},{"id":2400474,"title_ru":"Цдо","title_en":"Tsdo"},{"id":2400530,"title_ru":"Цедиси","title_en":"Tsedisi"},{"id":2400531,"title_ru":"Цеси","title_en":"Tsesi"},{"id":2400755,"title_ru":"Цилкани","title_en":"Tsilkani"},{"id":1910083,"title_ru":"Цинагари","title_en":"Tsinagari"},{"id":2400070,"title_ru":"Цинарети","title_en":"Tsinareti"},{"id":2400219,"title_ru":"Цинсопели","title_en":"Tsinsopeli"},{"id":2400677,"title_ru":"Цинубани","title_en":"Tsinubani"},{"id":1946059,"title_ru":"Цинцкаро","title_en":"Tsintskaro"},{"id":2400220,"title_ru":"Ципа","title_en":"Tsipa"},{"id":2400532,"title_ru":"Цифарчи","title_en":"Tsifarchi"},{"id":2400756,"title_ru":"Цифгина","title_en":"Tsifgina"},{"id":1912580,"title_ru":"Цихисджвари","title_en":"Tsikhisdzhvari"},{"id":1704410,"title_ru":"Цихисдзири","title_en":"Tsikhisdziri"},{"id":2400611,"title_ru":"Цкаваши","title_en":"Tskavashi"},{"id":2400143,"title_ru":"Цкалцминда","title_en":"Tskaltsminda"},{"id":2400401,"title_ru":"Цкнари-Абано","title_en":"Tsknari-Abano"},{"id":2400221,"title_ru":"Цкнори","title_en":"Tsknori"},{"id":5470335,"title_ru":"Цкрути","title_en":"Tskruti"},{"id":1706110,"title_ru":"Цнори","title_en":"Tsnori"},{"id":2400757,"title_ru":"Цоиси","title_en":"Tsoisi"},{"id":2400758,"title_ru":"Цру","title_en":"Tsru"},{"id":2400033,"title_ru":"Цугуровка","title_en":"Tsugurovka"},{"id":21627,"title_ru":"Цулукидзе","title_en":"Tsulukidze"},{"id":2400376,"title_ru":"Цуртави  (Колагири)","title_en":"Tsurtavi  (kolagiri)"},{"id":1905996,"title_ru":"Цхалтбила","title_en":"Tskhaltbila"},{"id":1708955,"title_ru":"Цхалтубо","title_en":"Tskhaltubo"},{"id":2400144,"title_ru":"Цхемлисхиди","title_en":"Tskhemliskhidi"},{"id":1940738,"title_ru":"Цхинвали \/ Цхинвал","title_en":"Tskhinvali \/ Tskhinval"},{"id":2400533,"title_ru":"Цхмори","title_en":"Tskhmori"},{"id":2400145,"title_ru":"Чаисубани","title_en":"Chaisubani"},{"id":1707114,"title_ru":"Чакви","title_en":"Chakvi"},{"id":2400071,"title_ru":"Чала","title_en":"Chala"},{"id":2400612,"title_ru":"Чале","title_en":"Chale"},{"id":2400402,"title_ru":"Чанахчи","title_en":"Chanakhchi"},{"id":2400146,"title_ru":"Чаниети","title_en":"Chanieti"},{"id":2400072,"title_ru":"Чарнали","title_en":"Charnali"},{"id":2400534,"title_ru":"Часавали","title_en":"Chasavali"},{"id":2400613,"title_ru":"Чвабиани","title_en":"Chvabiani"},{"id":2400535,"title_ru":"Челиагеле","title_en":"Cheliagele"},{"id":2400614,"title_ru":"Черноморский","title_en":"Chernomorsky"},{"id":21466,"title_ru":"Чиатура ","title_en":"Chiatura"},{"id":2400475,"title_ru":"Чигоиани","title_en":"Chigoiani"},{"id":2400476,"title_ru":"Чикаани","title_en":"Chikaani"},{"id":2400477,"title_ru":"Чимга","title_en":"Chimga"},{"id":2400478,"title_ru":"Чинчараанткари","title_en":"Chincharaantkari"},{"id":2400678,"title_ru":"Читахеви","title_en":"Chitakhevi"},{"id":2400615,"title_ru":"Читацкари","title_en":"Chitatskari"},{"id":2400536,"title_ru":"Чихареши","title_en":"Chikhareshi"},{"id":5470321,"title_ru":"Чкадуаши","title_en":"Chkaduashi"},{"id":2400537,"title_ru":"Чквиши","title_en":"Chkvishi"},{"id":1923461,"title_ru":"Члоу","title_en":"Chlou"},{"id":1968514,"title_ru":"Чогнари","title_en":"Chognari"},{"id":2400147,"title_ru":"Чохатаури","title_en":"Chokhatauri"},{"id":2400148,"title_ru":"Чочхати","title_en":"Chochkhati"},{"id":2400538,"title_ru":"Чребало","title_en":"Chrebalo"},{"id":1939937,"title_ru":"Чубурхинджи","title_en":"Chuburkhindzhi"},{"id":2201776,"title_ru":"Чумлаки","title_en":"Chumlaki"},{"id":2400479,"title_ru":"Чурта","title_en":"Churta"},{"id":2400149,"title_ru":"Чхакоура","title_en":"Chkhakoura"},{"id":2400760,"title_ru":"Чхараули","title_en":"Chkharauli"},{"id":5470323,"title_ru":"Чхориа","title_en":"Chkhoria"},{"id":1952720,"title_ru":"Чхороцку","title_en":"Chkhorotsku"},{"id":2400761,"title_ru":"Шавшвеби","title_en":"Shavshvebi"},{"id":2400224,"title_ru":"Шалаури","title_en":"Shalauri"},{"id":5470319,"title_ru":"Шамгона","title_en":"Shamgona"},{"id":2400404,"title_ru":"Шамта","title_en":"Shamta"},{"id":5470338,"title_ru":"Шарабидзееби","title_en":"Sharabidzeebi"},{"id":2400480,"title_ru":"Шатили","title_en":"Shatili"},{"id":1914708,"title_ru":"Шаумяни","title_en":"Shaumyani"},{"id":5470349,"title_ru":"Шахмарло","title_en":"Shakhmarlo"},{"id":2400481,"title_ru":"Шевардени","title_en":"Shevardeni"},{"id":2400150,"title_ru":"Шемокмеди","title_en":"Shemokmedi"},{"id":2400681,"title_ru":"Шида-Картлийский","title_en":"Shida-Kartliysky"},{"id":2400762,"title_ru":"Шихантури","title_en":"Shikhanturi"},{"id":1940386,"title_ru":"Шицкуара","title_en":"Shitskuara"},{"id":2400617,"title_ru":"Шкалери","title_en":"Shkaleri"},{"id":2400539,"title_ru":"Шкмери","title_en":"Shkmeri"},{"id":2400540,"title_ru":"Шови","title_en":"Shovi"},{"id":1965493,"title_ru":"Шрома","title_en":"Shroma"},{"id":2400618,"title_ru":"Шромискари","title_en":"Shromiskari"},{"id":2400541,"title_ru":"Шуа-Агви","title_en":"Shua-Agvi"},{"id":2400365,"title_ru":"Шуа-Болниси","title_en":"Shua-Bolnisi"},{"id":5470341,"title_ru":"Шуахеви","title_en":"Shuakhevi"},{"id":2400073,"title_ru":"Шубани","title_en":"Shubani"},{"id":2400225,"title_ru":"Шукрути","title_en":"Shukruti"},{"id":1962176,"title_ru":"Шулавери","title_en":"Shulaveri"},{"id":2400152,"title_ru":"Шухути","title_en":"Shukhuti"},{"id":2400679,"title_ru":"Элиацминда","title_en":"Eliatsminda"},{"id":1912443,"title_ru":"Эргета","title_en":"Ergeta"},{"id":2400763,"title_ru":"Эредви","title_en":"Eredvi"},{"id":2400482,"title_ru":"Эрето","title_en":"Ereto"},{"id":2400153,"title_ru":"Эркети","title_en":"Erketi"},{"id":2400406,"title_ru":"Эртиси","title_en":"Ertisi"},{"id":1944379,"title_ru":"Эстонка","title_en":"Estonka"},{"id":7720,"title_ru":"Эцери","title_en":"Etseri"},{"id":2400036,"title_ru":"Эшера","title_en":"Eshera"},{"id":1957987,"title_ru":"Эштия","title_en":"Eshtia"},{"id":5470347,"title_ru":"Яштхуа","title_en":"Yashtkhua"}]}